powertorch/__init__.py
powertorch/helper/__init__.py
powertorch/helper/data.py
powertorch/helper/helper.py
powertorch/models/__init__.py
powertorch/models/lenet5.py
powertorch/models/perceptron.py
powertorch/models/quantized.py
powertorch-0.1.0.dist-info/LICENSE
powertorch-0.1.0.dist-info/WHEEL
powertorch-0.1.0.dist-info/METADATA
powertorch-0.1.0.dist-info/RECORD
