Metadata-Version: 2.3
Name: powertorch
Version: 0.1.0
Summary: A collection of PyTorch utilities designed to streamline the deep learning workflows
Requires-Python: >=3.10
Requires-Dist: torch
Requires-Dist: torchvision
Project-URL: homepage, https://github.com/yutingshih/powertorch
